crdb_sql_audit/__init__.py
crdb_sql_audit/audit.py
crdb_sql_audit/main.py
crdb_sql_audit/roach-logo.svg
crdb_sql_audit/rules_engine.py
crdb_sql_audit/rules/postgres_to_crdb.yaml
crdb_sql_audit-0.2.8.dist-info/licenses/LICENSE
crdb_sql_audit-0.2.8.dist-info/METADATA
crdb_sql_audit-0.2.8.dist-info/WHEEL
crdb_sql_audit-0.2.8.dist-info/entry_points.txt
crdb_sql_audit-0.2.8.dist-info/top_level.txt
crdb_sql_audit-0.2.8.dist-info/RECORD
